mb_tron/__init__.py
mb_tron/cli/__init__.py
mb_tron/cli/cmd/__init__.py
mb_tron/cli/cmd/generate_account_cmd.py
mb_tron/tron/account.py
mb_tron/tron/trc20.py
mb_tron/tron/trx.py
mb_tron/tron/utils.py
mb_tron-0.1.1.dist-info/METADATA
mb_tron-0.1.1.dist-info/WHEEL
mb_tron-0.1.1.dist-info/entry_points.txt
mb_tron-0.1.1.dist-info/top_level.txt
mb_tron-0.1.1.dist-info/RECORD
